{
"meta":{"test_sets":[],"test_metrics":[],"learn_metrics":[{"best_value":"Min","name":"RMSE"}],"launch_mode":"Train","parameters":"","iteration_count":200,"learn_sets":["learn"],"name":"experiment"},
"iterations":[
{"learn":[0.3473230443],"iteration":0,"passed_time":0.002577016697,"remaining_time":0.5128263226},
{"learn":[0.3431565705],"iteration":1,"passed_time":0.005413033517,"remaining_time":0.5358903181},
{"learn":[0.3384597614],"iteration":2,"passed_time":0.007646204386,"remaining_time":0.5021007547},
{"learn":[0.3344842699],"iteration":3,"passed_time":0.009962004961,"remaining_time":0.4881382431},
{"learn":[0.3294914484],"iteration":4,"passed_time":0.01659281069,"remaining_time":0.6471196171},
{"learn":[0.325775962],"iteration":5,"passed_time":0.01897594609,"remaining_time":0.6135555901},
{"learn":[0.322154158],"iteration":6,"passed_time":0.0212031753,"remaining_time":0.5846018333},
{"learn":[0.3180957116],"iteration":7,"passed_time":0.02352754501,"remaining_time":0.5646610803},
{"learn":[0.3138638984],"iteration":8,"passed_time":0.02602382519,"remaining_time":0.5522834013},
{"learn":[0.3100278346],"iteration":9,"passed_time":0.03077544583,"remaining_time":0.5847334709},
{"learn":[0.3057797351],"iteration":10,"passed_time":0.03321739976,"remaining_time":0.5707353231},
{"learn":[0.3024196066],"iteration":11,"passed_time":0.03552327617,"remaining_time":0.5565313267},
{"learn":[0.2987055464],"iteration":12,"passed_time":0.04608319624,"remaining_time":0.6628890535},
{"learn":[0.294916789],"iteration":13,"passed_time":0.04894751607,"remaining_time":0.6503027135},
{"learn":[0.2915373705],"iteration":14,"passed_time":0.05120613095,"remaining_time":0.6315422818},
{"learn":[0.2883899614],"iteration":15,"passed_time":0.05363162236,"remaining_time":0.6167636572},
{"learn":[0.2852188898],"iteration":16,"passed_time":0.05597448625,"remaining_time":0.6025488814},
{"learn":[0.2823692901],"iteration":17,"passed_time":0.06094479882,"remaining_time":0.6162196325},
{"learn":[0.2790738371],"iteration":18,"passed_time":0.06380304945,"remaining_time":0.6078079974},
{"learn":[0.2763327272],"iteration":19,"passed_time":0.06884333611,"remaining_time":0.619590025},
{"learn":[0.2741106279],"iteration":20,"passed_time":0.07119819907,"remaining_time":0.6068798873},
{"learn":[0.2716203694],"iteration":21,"passed_time":0.07385730818,"remaining_time":0.5975727662},
{"learn":[0.2689639083],"iteration":22,"passed_time":0.07734323809,"remaining_time":0.5952066584},
{"learn":[0.2663020975],"iteration":23,"passed_time":0.07957370766,"remaining_time":0.5835405228},
{"learn":[0.2634729312],"iteration":24,"passed_time":0.08186338671,"remaining_time":0.5730437069},
{"learn":[0.2608734988],"iteration":25,"passed_time":0.08464832155,"remaining_time":0.5664926134},
{"learn":[0.2580149443],"iteration":26,"passed_time":0.09171115002,"remaining_time":0.587630702},
{"learn":[0.2560167042],"iteration":27,"passed_time":0.09431068358,"remaining_time":0.5793370563},
{"learn":[0.2532689927],"iteration":28,"passed_time":0.09658010676,"remaining_time":0.569489595},
{"learn":[0.2512388341],"iteration":29,"passed_time":0.09888071597,"remaining_time":0.5603240572},
{"learn":[0.249319023],"iteration":30,"passed_time":0.1012039382,"remaining_time":0.5517246951},
{"learn":[0.2470899885],"iteration":31,"passed_time":0.1055760534,"remaining_time":0.5542742805},
{"learn":[0.2453883721],"iteration":32,"passed_time":0.1115358685,"remaining_time":0.5644390923},
{"learn":[0.2438420751],"iteration":33,"passed_time":0.1144633376,"remaining_time":0.5588504127},
{"learn":[0.2419795573],"iteration":34,"passed_time":0.1168371503,"remaining_time":0.5508037085},
{"learn":[0.2400112698],"iteration":35,"passed_time":0.1209001449,"remaining_time":0.5507673268},
{"learn":[0.2384805956],"iteration":36,"passed_time":0.1278481241,"remaining_time":0.563222817},
{"learn":[0.2366124519],"iteration":37,"passed_time":0.1306635229,"remaining_time":0.5570392293},
{"learn":[0.23545751],"iteration":38,"passed_time":0.1338770497,"remaining_time":0.5526719232},
{"learn":[0.2337491722],"iteration":39,"passed_time":0.1384689271,"remaining_time":0.5538757085},
{"learn":[0.2322934219],"iteration":40,"passed_time":0.1403136692,"remaining_time":0.5441432539},
{"learn":[0.2306464],"iteration":41,"passed_time":0.142515869,"remaining_time":0.5361311262},
{"learn":[0.2293945834],"iteration":42,"passed_time":0.1448026781,"remaining_time":0.5286981503},
{"learn":[0.228010398],"iteration":43,"passed_time":0.1480910622,"remaining_time":0.5250501297},
{"learn":[0.2267978693],"iteration":44,"passed_time":0.1505061267,"remaining_time":0.5184099919},
{"learn":[0.2254291206],"iteration":45,"passed_time":0.1534530456,"remaining_time":0.5137341093},
{"learn":[0.2240236168],"iteration":46,"passed_time":0.1556989027,"remaining_time":0.5068496194},
{"learn":[0.2227637758],"iteration":47,"passed_time":0.157967886,"remaining_time":0.500231639},
{"learn":[0.2215140208],"iteration":48,"passed_time":0.1602654021,"remaining_time":0.4938790962},
{"learn":[0.220139793],"iteration":49,"passed_time":0.1625607205,"remaining_time":0.4876821615},
{"learn":[0.218717461],"iteration":50,"passed_time":0.1648687207,"remaining_time":0.4816752822},
{"learn":[0.2175934839],"iteration":51,"passed_time":0.1685669466,"remaining_time":0.4797674635},
{"learn":[0.2166615714],"iteration":52,"passed_time":0.171091176,"remaining_time":0.4745359032},
{"learn":[0.2155106029],"iteration":53,"passed_time":0.1734268363,"remaining_time":0.4688947795},
{"learn":[0.21450093],"iteration":54,"passed_time":0.1761264147,"remaining_time":0.4643332752},
{"learn":[0.2134374403],"iteration":55,"passed_time":0.1783428702,"remaining_time":0.4585959519},
{"learn":[0.2124637367],"iteration":56,"passed_time":0.1808672568,"remaining_time":0.4537546969},
{"learn":[0.2116250767],"iteration":57,"passed_time":0.1836360795,"remaining_time":0.4495917808},
{"learn":[0.210495688],"iteration":58,"passed_time":0.1860805054,"remaining_time":0.4447008688},
{"learn":[0.2096358736],"iteration":59,"passed_time":0.1882814121,"remaining_time":0.4393232949},
{"learn":[0.2086897482],"iteration":60,"passed_time":0.1907159864,"remaining_time":0.4345823296},
{"learn":[0.2074689307],"iteration":61,"passed_time":0.193021702,"remaining_time":0.4296289497},
{"learn":[0.2066276996],"iteration":62,"passed_time":0.1952591974,"remaining_time":0.4246112706},
{"learn":[0.205932836],"iteration":63,"passed_time":0.1989962105,"remaining_time":0.4228669473},
{"learn":[0.2052166808],"iteration":64,"passed_time":0.2015896495,"remaining_time":0.4186861952},
{"learn":[0.2042979901],"iteration":65,"passed_time":0.2040451567,"remaining_time":0.4142735},
{"learn":[0.2030641405],"iteration":66,"passed_time":0.2063987835,"remaining_time":0.4097169881},
{"learn":[0.202248074],"iteration":67,"passed_time":0.2087788139,"remaining_time":0.4052765212},
{"learn":[0.2013948399],"iteration":68,"passed_time":0.2112650284,"remaining_time":0.4010973728},
{"learn":[0.2005053214],"iteration":69,"passed_time":0.2154213741,"remaining_time":0.4000682662},
{"learn":[0.1998310173],"iteration":70,"passed_time":0.2177741801,"remaining_time":0.3956742145},
{"learn":[0.1991686965],"iteration":71,"passed_time":0.2201869451,"remaining_time":0.391443458},
{"learn":[0.1984563512],"iteration":72,"passed_time":0.2227234483,"remaining_time":0.3874777799},
{"learn":[0.1980049474],"iteration":73,"passed_time":0.2250978062,"remaining_time":0.383274643},
{"learn":[0.1974154674],"iteration":74,"passed_time":0.2295043033,"remaining_time":0.3825071722},
{"learn":[0.1967390936],"iteration":75,"passed_time":0.2319869791,"remaining_time":0.3785050712},
{"learn":[0.1962384998],"iteration":76,"passed_time":0.2344078219,"remaining_time":0.3744436635},
{"learn":[0.1957277311],"iteration":77,"passed_time":0.2367256475,"remaining_time":0.3702631923},
{"learn":[0.1951806003],"iteration":78,"passed_time":0.239013201,"remaining_time":0.3660835104},
{"learn":[0.1945534657],"iteration":79,"passed_time":0.2428676913,"remaining_time":0.3643015369},
{"learn":[0.1937114472],"iteration":80,"passed_time":0.2456175681,"remaining_time":0.360845563},
{"learn":[0.1931678101],"iteration":81,"passed_time":0.2480609198,"remaining_time":0.3569657139},
{"learn":[0.1926036609],"iteration":82,"passed_time":0.2503936818,"remaining_time":0.3529645876},
{"learn":[0.1920149895],"iteration":83,"passed_time":0.2526217982,"remaining_time":0.3488586737},
{"learn":[0.1911716116],"iteration":84,"passed_time":0.2548771033,"remaining_time":0.3448337279},
{"learn":[0.1906219975],"iteration":85,"passed_time":0.2584675367,"remaining_time":0.342619758},
{"learn":[0.1899494618],"iteration":86,"passed_time":0.2614424119,"remaining_time":0.3395746269},
{"learn":[0.1894163987],"iteration":87,"passed_time":0.2638053063,"remaining_time":0.335752208},
{"learn":[0.1887305392],"iteration":88,"passed_time":0.2662520595,"remaining_time":0.3320671754},
{"learn":[0.188070289],"iteration":89,"passed_time":0.2684888316,"remaining_time":0.3281530164},
{"learn":[0.1876418292],"iteration":90,"passed_time":0.2709663441,"remaining_time":0.3245640825},
{"learn":[0.1870447859],"iteration":91,"passed_time":0.2756432175,"remaining_time":0.3235811684},
{"learn":[0.1865356539],"iteration":92,"passed_time":0.2780845752,"remaining_time":0.3199467693},
{"learn":[0.185964159],"iteration":93,"passed_time":0.2804709767,"remaining_time":0.3162757822},
{"learn":[0.1854536844],"iteration":94,"passed_time":0.2828511876,"remaining_time":0.3126249968},
{"learn":[0.1850543607],"iteration":95,"passed_time":0.2852779789,"remaining_time":0.3090511439},
{"learn":[0.1847277153],"iteration":96,"passed_time":0.2878192955,"remaining_time":0.3056225509},
{"learn":[0.1844479003],"iteration":97,"passed_time":0.2909062662,"remaining_time":0.3027799913},
{"learn":[0.1839243442],"iteration":98,"passed_time":0.2930781142,"remaining_time":0.2989988842},
{"learn":[0.1835999082],"iteration":99,"passed_time":0.2953327689,"remaining_time":0.2953327689},
{"learn":[0.183166112],"iteration":100,"passed_time":0.2977334785,"remaining_time":0.291837766},
{"learn":[0.1825242831],"iteration":101,"passed_time":0.2999790158,"remaining_time":0.2882151328},
{"learn":[0.1821783612],"iteration":102,"passed_time":0.302175608,"remaining_time":0.2845731454},
{"learn":[0.1819633859],"iteration":103,"passed_time":0.3058054818,"remaining_time":0.2822819832},
{"learn":[0.1817325871],"iteration":104,"passed_time":0.3082684276,"remaining_time":0.2789095297},
{"learn":[0.1810671585],"iteration":105,"passed_time":0.3107094153,"remaining_time":0.2755347645},
{"learn":[0.180721147],"iteration":106,"passed_time":0.3129773808,"remaining_time":0.2720270693},
{"learn":[0.1803230164],"iteration":107,"passed_time":0.3166157878,"remaining_time":0.2697097452},
{"learn":[0.1799844336],"iteration":108,"passed_time":0.3212416727,"remaining_time":0.2681925891},
{"learn":[0.1797638742],"iteration":109,"passed_time":0.3239342205,"remaining_time":0.2650370895},
{"learn":[0.1795675779],"iteration":110,"passed_time":0.3262312902,"remaining_time":0.2615728363},
{"learn":[0.1792043887],"iteration":111,"passed_time":0.3284383194,"remaining_time":0.2580586796},
{"learn":[0.1789670957],"iteration":112,"passed_time":0.3306647056,"remaining_time":0.2545825609},
{"learn":[0.1788582117],"iteration":113,"passed_time":0.3327415579,"remaining_time":0.2510155612},
{"learn":[0.1783797988],"iteration":114,"passed_time":0.3374132406,"remaining_time":0.2493923952},
{"learn":[0.1783110255],"iteration":115,"passed_time":0.3390129923,"remaining_time":0.2454921668},
{"learn":[0.1779770673],"iteration":116,"passed_time":0.341456417,"remaining_time":0.2422297659},
{"learn":[0.1778226109],"iteration":117,"passed_time":0.3441369138,"remaining_time":0.2391459909},
{"learn":[0.1776203715],"iteration":118,"passed_time":0.3465281535,"remaining_time":0.2358721045},
{"learn":[0.1774682237],"iteration":119,"passed_time":0.3488788317,"remaining_time":0.2325858878},
{"learn":[0.1772544429],"iteration":120,"passed_time":0.3549658516,"remaining_time":0.2317545643},
{"learn":[0.1769866387],"iteration":121,"passed_time":0.3585263519,"remaining_time":0.229221766},
{"learn":[0.1767952835],"iteration":122,"passed_time":0.3610976458,"remaining_time":0.2260529978},
{"learn":[0.1766306448],"iteration":123,"passed_time":0.3636895926,"remaining_time":0.2229065245},
{"learn":[0.1762642239],"iteration":124,"passed_time":0.3690328953,"remaining_time":0.2214197372},
{"learn":[0.1761088542],"iteration":125,"passed_time":0.3716830077,"remaining_time":0.2182900204},
{"learn":[0.1760206403],"iteration":126,"passed_time":0.3740049076,"remaining_time":0.2149791988},
{"learn":[0.1757064688],"iteration":127,"passed_time":0.3762961374,"remaining_time":0.2116665773},
{"learn":[0.1754919876],"iteration":128,"passed_time":0.3785250566,"remaining_time":0.2083354963},
{"learn":[0.1753097473],"iteration":129,"passed_time":0.380768675,"remaining_time":0.2050292865},
{"learn":[0.175116919],"iteration":130,"passed_time":0.388053361,"remaining_time":0.2043945184},
{"learn":[0.1748038195],"iteration":131,"passed_time":0.3908877861,"remaining_time":0.2013664352},
{"learn":[0.1746826857],"iteration":132,"passed_time":0.3936309105,"remaining_time":0.1982952707},
{"learn":[0.1743314886],"iteration":133,"passed_time":0.3961960474,"remaining_time":0.1951413368},
{"learn":[0.1739964729],"iteration":134,"passed_time":0.4006734066,"remaining_time":0.1929168254},
{"learn":[0.173559455],"iteration":135,"passed_time":0.4038339342,"remaining_time":0.1900394985},
{"learn":[0.1732814984],"iteration":136,"passed_time":0.4124278879,"remaining_time":0.18965662},
{"learn":[0.173016753],"iteration":137,"passed_time":0.4185763097,"remaining_time":0.1880560232},
{"learn":[0.1727562534],"iteration":138,"passed_time":0.4210446879,"remaining_time":0.1847750069},
{"learn":[0.1725105932],"iteration":139,"passed_time":0.4238708212,"remaining_time":0.1816589234},
{"learn":[0.1724060227],"iteration":140,"passed_time":0.4263241971,"remaining_time":0.1783909761},
{"learn":[0.1720315787],"iteration":141,"passed_time":0.4321728999,"remaining_time":0.1765213253},
{"learn":[0.1717550135],"iteration":142,"passed_time":0.4385334674,"remaining_time":0.1748000535},
{"learn":[0.1716593331],"iteration":143,"passed_time":0.4419072267,"remaining_time":0.1718528104},
{"learn":[0.1714628196],"iteration":144,"passed_time":0.4444175651,"remaining_time":0.1685721799},
{"learn":[0.1712820924],"iteration":145,"passed_time":0.4504113405,"remaining_time":0.1665904958},
{"learn":[0.1711415314],"iteration":146,"passed_time":0.4529336133,"remaining_time":0.1633025953},
{"learn":[0.1709758597],"iteration":147,"passed_time":0.4554649393,"remaining_time":0.1600282219},
{"learn":[0.1708387424],"iteration":148,"passed_time":0.4587495095,"remaining_time":0.1570216442},
{"learn":[0.1705715481],"iteration":149,"passed_time":0.4676969947,"remaining_time":0.1558989982},
{"learn":[0.1703700935],"iteration":150,"passed_time":0.470441237,"remaining_time":0.1526597391},
{"learn":[0.1702203352],"iteration":151,"passed_time":0.4727514602,"remaining_time":0.1492899348},
{"learn":[0.1699755274],"iteration":152,"passed_time":0.4752121245,"remaining_time":0.1459801951},
{"learn":[0.1698510194],"iteration":153,"passed_time":0.4805449064,"remaining_time":0.1435393876},
{"learn":[0.1696863665],"iteration":154,"passed_time":0.4841382989,"remaining_time":0.1405562803},
{"learn":[0.1694396976],"iteration":155,"passed_time":0.4872473335,"remaining_time":0.1374287351},
{"learn":[0.169327599],"iteration":156,"passed_time":0.4899442203,"remaining_time":0.1341885444},
{"learn":[0.1689935353],"iteration":157,"passed_time":0.4922067919,"remaining_time":0.1308397801},
{"learn":[0.1688896602],"iteration":158,"passed_time":0.4963435457,"remaining_time":0.1279879583},
{"learn":[0.1687237941],"iteration":159,"passed_time":0.4985607066,"remaining_time":0.1246401766},
{"learn":[0.1685875414],"iteration":160,"passed_time":0.5010624427,"remaining_time":0.1213753743},
{"learn":[0.1684638906],"iteration":161,"passed_time":0.503297557,"remaining_time":0.1180574516},
{"learn":[0.1682727933],"iteration":162,"passed_time":0.505604501,"remaining_time":0.1147691199},
{"learn":[0.1679916067],"iteration":163,"passed_time":0.5101152042,"remaining_time":0.1119765082},
{"learn":[0.1678502687],"iteration":164,"passed_time":0.5125466202,"remaining_time":0.1087220103},
{"learn":[0.167539713],"iteration":165,"passed_time":0.5152594523,"remaining_time":0.1055350685},
{"learn":[0.1674548085],"iteration":166,"passed_time":0.5179566554,"remaining_time":0.1023507163},
{"learn":[0.1671913261],"iteration":167,"passed_time":0.5213463503,"remaining_time":0.09930406673},
{"learn":[0.1669028959],"iteration":168,"passed_time":0.5284674574,"remaining_time":0.09693781763},
{"learn":[0.1666950049],"iteration":169,"passed_time":0.5313112514,"remaining_time":0.09376080907},
{"learn":[0.1665275014],"iteration":170,"passed_time":0.5346493896,"remaining_time":0.0906715339},
{"learn":[0.1662752197],"iteration":171,"passed_time":0.537496406,"remaining_time":0.08749941493},
{"learn":[0.1662136909],"iteration":172,"passed_time":0.5422534349,"remaining_time":0.0846291488},
{"learn":[0.1660487154],"iteration":173,"passed_time":0.5451285329,"remaining_time":0.08145598768},
{"learn":[0.1658715384],"iteration":174,"passed_time":0.5474525012,"remaining_time":0.07820750017},
{"learn":[0.1656905116],"iteration":175,"passed_time":0.5502188112,"remaining_time":0.0750298379},
{"learn":[0.1655765491],"iteration":176,"passed_time":0.5550976,"remaining_time":0.07213132655},
{"learn":[0.1655203623],"iteration":177,"passed_time":0.5579696398,"remaining_time":0.06896253975},
{"learn":[0.1653376138],"iteration":178,"passed_time":0.5610527524,"remaining_time":0.06582183129},
{"learn":[0.1653097562],"iteration":179,"passed_time":0.5627696319,"remaining_time":0.0625299591},
{"learn":[0.1649500063],"iteration":180,"passed_time":0.5651159794,"remaining_time":0.0593215669},
{"learn":[0.1648398971],"iteration":181,"passed_time":0.5707099726,"remaining_time":0.05644384345},
{"learn":[0.1646742832],"iteration":182,"passed_time":0.574031712,"remaining_time":0.0533253503},
{"learn":[0.1645658259],"iteration":183,"passed_time":0.5765108518,"remaining_time":0.05013137841},
{"learn":[0.1644970756],"iteration":184,"passed_time":0.5790695023,"remaining_time":0.04695158127},
{"learn":[0.1644448053],"iteration":185,"passed_time":0.5814932975,"remaining_time":0.04376831271},
{"learn":[0.1644050633],"iteration":186,"passed_time":0.5876243351,"remaining_time":0.0408508896},
{"learn":[0.1642992063],"iteration":187,"passed_time":0.5901674941,"remaining_time":0.03767026558},
{"learn":[0.1641785196],"iteration":188,"passed_time":0.5927337554,"remaining_time":0.03449773179},
{"learn":[0.1640829256],"iteration":189,"passed_time":0.595244822,"remaining_time":0.03132867484},
{"learn":[0.1638646035],"iteration":190,"passed_time":0.5980913422,"remaining_time":0.02818231455},
{"learn":[0.1636684951],"iteration":191,"passed_time":0.6040879893,"remaining_time":0.02517033289},
{"learn":[0.1633943426],"iteration":192,"passed_time":0.6066183774,"remaining_time":0.02200170281},
{"learn":[0.1632641601],"iteration":193,"passed_time":0.6115104014,"remaining_time":0.01891269283},
{"learn":[0.1630609066],"iteration":194,"passed_time":0.6148172404,"remaining_time":0.01576454462},
{"learn":[0.1629543098],"iteration":195,"passed_time":0.618194575,"remaining_time":0.01261621582},
{"learn":[0.1628596306],"iteration":196,"passed_time":0.6209255212,"remaining_time":0.009455718597},
{"learn":[0.1628041304],"iteration":197,"passed_time":0.6232752537,"remaining_time":0.006295709633},
{"learn":[0.162709002],"iteration":198,"passed_time":0.6255570237,"remaining_time":0.003143502631},
{"learn":[0.1626262847],"iteration":199,"passed_time":0.6328043177,"remaining_time":0}
]}